cumulus/__init__.py
cumulus/_version.py
cumulus/authentication.py
cumulus/context_processors.py
cumulus/models.py
cumulus/settings.py
cumulus/storage.py
cumulus/management/__init__.py
cumulus/management/commands/__init__.py
cumulus/management/commands/collectstatic.py
cumulus/management/commands/container_create.py
cumulus/management/commands/container_delete.py
cumulus/management/commands/container_info.py
cumulus/management/commands/container_list.py
cumulus/management/commands/syncfiles.py
cumulus/tests/__init__.py
cumulus/tests/models.py
cumulus/tests/test_storage.py
django_cumulus-1.0.21.dist-info/DESCRIPTION.rst
django_cumulus-1.0.21.dist-info/METADATA
django_cumulus-1.0.21.dist-info/RECORD
django_cumulus-1.0.21.dist-info/WHEEL
django_cumulus-1.0.21.dist-info/metadata.json
django_cumulus-1.0.21.dist-info/top_level.txt
example/__init__.py
example/manage.py
example/urls.py
example/photos/__init__.py
example/photos/admin.py
example/photos/models.py
example/photos/views.py
example/settings/__init__.py
example/settings/common.py
example/settings/legacy.py
example/settings/test.py
