Metadata-Version: 2.0
Name: django-cumulus
Version: 1.0.21
Summary: An interface to python-swiftclient and rackspace cloudfiles API from Django.
Home-page: https://github.com/django-cumulus/django-cumulus/
Author: Ferrix Hovi, Thomas Schreiber
Author-email: UNKNOWN
License: BSD
Platform: UNKNOWN
Classifier: Development Status :: 5 - Production/Stable
Classifier: Environment :: Web Environment
Classifier: Intended Audience :: Developers
Classifier: License :: OSI Approved :: BSD License
Classifier: Operating System :: OS Independent
Classifier: Programming Language :: Python
Classifier: Framework :: Django
Requires-Dist: pyrax (<1.10,>=1.9)
